numLetterFing/__init__.py
numLetterFing/numLetterFinglishi.py
numLetterFinglishi_pkg_Rufo-0.0.1.dist-info/METADATA
numLetterFinglishi_pkg_Rufo-0.0.1.dist-info/WHEEL
numLetterFinglishi_pkg_Rufo-0.0.1.dist-info/top_level.txt
numLetterFinglishi_pkg_Rufo-0.0.1.dist-info/RECORD
