Metadata-Version: 2.1
Name: numLetterFinglishi-pkg-Rufo
Version: 0.0.1
Summary: A small small small insignificent package
Home-page: https://github.com/pypa/sampleproject
Author: Raouf Farhang
Author-email: raouf.farhang@gmail.com
License: UNKNOWN
Project-URL: Bug Tracker, https://github.com/pypa/sampleproject/issues
Platform: UNKNOWN
Classifier: Programming Language :: Python :: 3
Classifier: License :: OSI Approved :: MIT License
Classifier: Operating System :: OS Independent
Requires-Python: >=3.6
